huaweicloudsdkcts/__init__.py
huaweicloudsdkcts/v3/__init__.py
huaweicloudsdkcts/v3/cts_async_client.py
huaweicloudsdkcts/v3/cts_client.py
huaweicloudsdkcts/v3/model/__init__.py
huaweicloudsdkcts/v3/model/attributes.py
huaweicloudsdkcts/v3/model/base_user.py
huaweicloudsdkcts/v3/model/batch_create_resource_tags_request.py
huaweicloudsdkcts/v3/model/batch_create_resource_tags_request_body.py
huaweicloudsdkcts/v3/model/batch_create_resource_tags_response.py
huaweicloudsdkcts/v3/model/batch_delete_resource_tags_request.py
huaweicloudsdkcts/v3/model/batch_delete_resource_tags_request_body.py
huaweicloudsdkcts/v3/model/batch_delete_resource_tags_response.py
huaweicloudsdkcts/v3/model/bucket.py
huaweicloudsdkcts/v3/model/check_bucket_request.py
huaweicloudsdkcts/v3/model/check_bucket_response.py
huaweicloudsdkcts/v3/model/check_obs_buckets_request.py
huaweicloudsdkcts/v3/model/check_obs_buckets_request_body.py
huaweicloudsdkcts/v3/model/check_obs_buckets_response.py
huaweicloudsdkcts/v3/model/create_notification_request.py
huaweicloudsdkcts/v3/model/create_notification_request_body.py
huaweicloudsdkcts/v3/model/create_notification_response.py
huaweicloudsdkcts/v3/model/create_tracker_request.py
huaweicloudsdkcts/v3/model/create_tracker_request_body.py
huaweicloudsdkcts/v3/model/create_tracker_response.py
huaweicloudsdkcts/v3/model/cts_quota.py
huaweicloudsdkcts/v3/model/data_bucket.py
huaweicloudsdkcts/v3/model/data_bucket_query.py
huaweicloudsdkcts/v3/model/delete_notification_request.py
huaweicloudsdkcts/v3/model/delete_notification_response.py
huaweicloudsdkcts/v3/model/delete_tracker_request.py
huaweicloudsdkcts/v3/model/delete_tracker_response.py
huaweicloudsdkcts/v3/model/filter.py
huaweicloudsdkcts/v3/model/list_notifications_request.py
huaweicloudsdkcts/v3/model/list_notifications_response.py
huaweicloudsdkcts/v3/model/list_operation.py
huaweicloudsdkcts/v3/model/list_operations_request.py
huaweicloudsdkcts/v3/model/list_operations_response.py
huaweicloudsdkcts-3.1.184.dist-info/METADATA
huaweicloudsdkcts-3.1.184.dist-info/WHEEL
huaweicloudsdkcts-3.1.184.dist-info/licenses/LICENSE
huaweicloudsdkcts-3.1.184.dist-info/RECORD
